asort/__init__.py
asort/__main__.py
asort/__version__.py
asort/api.py
asort/main.py
asort-0.1.3.data/data/asort.version/VERSION.txt
asort-0.1.3.dist-info/LICENSE
asort-0.1.3.dist-info/METADATA
asort-0.1.3.dist-info/WHEEL
asort-0.1.3.dist-info/entry_points.txt
asort-0.1.3.dist-info/top_level.txt
asort-0.1.3.dist-info/RECORD
