Metadata-Version: 2.1
Name: asort
Version: 0.1.3
Summary: A Python utility / library to sort __all__ lists.
Home-page: https://github.com/cpendery/asort
Author: cpendery
Project-URL: Bug Tracker, https://github.com/cpendery/asort/issues
Classifier: Programming Language :: Python :: 3
Classifier: Programming Language :: Python :: 3 :: Only
Classifier: Programming Language :: Python :: 3.7
Classifier: Programming Language :: Python :: 3.8
Classifier: Programming Language :: Python :: 3.9
Classifier: Programming Language :: Python :: 3.10
Classifier: License :: OSI Approved :: Apache Software License
Classifier: Operating System :: OS Independent
Requires-Python: >=3.7
License-File: LICENSE
